Demo/__init__.py
Demo/demo.py
tkitDemo-0.0.0.216326670.dist-info/LICENSE
tkitDemo-0.0.0.216326670.dist-info/METADATA
tkitDemo-0.0.0.216326670.dist-info/WHEEL
tkitDemo-0.0.0.216326670.dist-info/top_level.txt
tkitDemo-0.0.0.216326670.dist-info/RECORD
