Metadata-Version: 2.1
Name: tkitDemo
Version: 0.0.0.216326670
Summary: Terry toolkit Demo,
Home-page: http://docs.terrychan.org/tkit-lr-pytorch/
Author: Terry Chan
Author-email: napoler2008@gmail.com
License: UNKNOWN
Platform: UNKNOWN
